.keep
cinje/__init__.py
cinje/__main__.py
cinje/encoding.py
cinje/helpers.py
cinje/release.py
cinje/util.py
cinje/__pycache__/__init__.cpython-37.opt-1.pyc
cinje/__pycache__/__main__.cpython-37.opt-1.pyc
cinje/__pycache__/encoding.cpython-37.opt-1.pyc
cinje/__pycache__/helpers.cpython-37.opt-1.pyc
cinje/__pycache__/release.cpython-37.opt-1.pyc
cinje/__pycache__/util.cpython-37.opt-1.pyc
cinje/block/__init__.py
cinje/block/function.py
cinje/block/generic.py
cinje/block/module.py
cinje/block/using.py
cinje/block/__pycache__/__init__.cpython-37.opt-1.pyc
cinje/block/__pycache__/function.cpython-37.opt-1.pyc
cinje/block/__pycache__/generic.cpython-37.opt-1.pyc
cinje/block/__pycache__/module.cpython-37.opt-1.pyc
cinje/block/__pycache__/using.cpython-37.opt-1.pyc
cinje/inline/__init__.py
cinje/inline/blank.py
cinje/inline/code.py
cinje/inline/comment.py
cinje/inline/flush.py
cinje/inline/pragma.py
cinje/inline/require.py
cinje/inline/text.py
cinje/inline/use.py
cinje/inline/__pycache__/__init__.cpython-37.opt-1.pyc
cinje/inline/__pycache__/blank.cpython-37.opt-1.pyc
cinje/inline/__pycache__/code.cpython-37.opt-1.pyc
cinje/inline/__pycache__/comment.cpython-37.opt-1.pyc
cinje/inline/__pycache__/flush.cpython-37.opt-1.pyc
cinje/inline/__pycache__/pragma.cpython-37.opt-1.pyc
cinje/inline/__pycache__/require.cpython-37.opt-1.pyc
cinje/inline/__pycache__/text.cpython-37.opt-1.pyc
cinje/inline/__pycache__/use.cpython-37.opt-1.pyc
cinje/std/__init__.py
cinje/std/html.py
cinje/std/__pycache__/__init__.cpython-37.opt-1.pyc
cinje/std/form/__init__.py
cinje/std/form/input.py
cinje/std/form/select.py
cinje/std/form/__pycache__/__init__.cpython-37.opt-1.pyc
cinje-1.1.2.dist-info/LICENSE.txt
cinje-1.1.2.dist-info/METADATA
cinje-1.1.2.dist-info/WHEEL
cinje-1.1.2.dist-info/entry_points.txt
cinje-1.1.2.dist-info/namespace_packages.txt
cinje-1.1.2.dist-info/top_level.txt
cinje-1.1.2.dist-info/zip-safe
cinje-1.1.2.dist-info/RECORD
