Metadata-Version: 2.1
Name: cinje
Version: 1.1.2
Summary: A Pythonic and ultra fast template engine DSL.
Home-page: https://github.com/marrow/cinje/
Author: Alice Bevan-McGregor
Author-email: alice@gothcandy.com
License: MIT
Download-URL: https://github.com/marrow/cinje/releases
Keywords: template,source translation,dsl,streaming,chunked
Platform: UNKNOWN
Classifier: Development Status :: 5 - Production/Stable
Classifier: Environment :: Console
Classifier: Environment :: Web Environment
Classifier: Intended Audience :: Developers
Classifier: License :: OSI Approved :: MIT License
Classifier: Operating System :: OS Independent
Classifier: Programming Language :: Python :: 2
Classifier: Programming Language :: Python :: 2.7
Classifier: Programming Language :: Python :: 3
Classifier: Programming Language :: Python :: 3.2
Classifier: Programming Language :: Python :: 3.3
Classifier: Programming Language :: Python :: 3.4
Classifier: Programming Language :: Python :: 3.5
Classifier: Programming Language :: Python :: 3.6
Classifier: Programming Language :: Python :: 3.7
Classifier: Programming Language :: Python :: Implementation :: CPython
Classifier: Programming Language :: Python :: Implementation :: PyPy
Classifier: Programming Language :: Python
Classifier: Topic :: Internet :: WWW/HTTP :: Dynamic Content
Classifier: Topic :: Internet :: WWW/HTTP :: WSGI
Classifier: Topic :: Software Development :: Libraries :: Python Modules
Classifier: Topic :: Software Development :: Libraries
Classifier: Topic :: Utilities
Provides-Extra: development
Requires-Dist: pytest ; extra == 'development'
Requires-Dist: pytest-cov ; extra == 'development'
Requires-Dist: pytest-flakes ; extra == 'development'
Requires-Dist: markupsafe ; extra == 'development'
Requires-Dist: pre-commit ; extra == 'development'
Provides-Extra: safe
Requires-Dist: webob ; extra == 'safe'
